covid19tracker.py
covid19_tracker-0.0.8.dist-info/LICENSE
covid19_tracker-0.0.8.dist-info/METADATA
covid19_tracker-0.0.8.dist-info/WHEEL
covid19_tracker-0.0.8.dist-info/top_level.txt
covid19_tracker-0.0.8.dist-info/RECORD
