Metadata-Version: 2.1
Name: covid19-tracker
Version: 0.0.8
Summary: This module helps to track Covid19.
Home-page: https://github.com/Ajay2810-hub/covid19-tracker
Author: Ajay Lingayat
Author-email: lingayatajay2810@gmail.com
License: UNKNOWN
Platform: UNKNOWN
Classifier: Programming Language :: Python :: 3
Classifier: License :: OSI Approved :: MIT License
Classifier: Operating System :: OS Independent
Requires-Python: >=3.6
Requires-Dist: bs4
Requires-Dist: requests
Requires-Dist: regex
Provides-Extra: dev
Requires-Dist: pytest (>=3.7) ; extra == 'dev'
